drfaddons/__init__.py
drfaddons/admin.py
drfaddons/auth.py
drfaddons/datatypes.py
drfaddons/filters.py
drfaddons/generics.py
drfaddons/mixins.py
drfaddons/models.py
drfaddons/permissions.py
drfaddons/serializers.py
drfaddons/test.py
drfaddons/utils.py
drfaddons/views.py
drfaddons-0.1.4.dist-info/LICENSE
drfaddons-0.1.4.dist-info/METADATA
drfaddons-0.1.4.dist-info/WHEEL
drfaddons-0.1.4.dist-info/top_level.txt
drfaddons-0.1.4.dist-info/RECORD
